viecpro_vis/__init__.py
viecpro_vis/admin.py
viecpro_vis/api_views.py
viecpro_vis/apps.py
viecpro_vis/forms.py
viecpro_vis/migrations/__init__.py
viecpro_vis/models.py
viecpro_vis/static/vis/css/autocomplete.css
viecpro_vis/static/vis/css/style.css
viecpro_vis/static/vis/js/autocomplete.js
viecpro_vis/static/vis/js/autocomplete.js.map
viecpro_vis/static/vis/js/d3.js
viecpro_vis/static/vis/js/graph.js
viecpro_vis/static/vis/js/organigramm.js
viecpro_vis/static/vis/js/sankey.js
viecpro_vis/static/vis/js/tree_new.js
viecpro_vis/templates/vis_base.html
viecpro_vis/tests.py
viecpro_vis/tree_functions.py
viecpro_vis/urls.py
viecpro_vis/views.py
viecpro_vis-0.1.10.dist-info/WHEEL
viecpro_vis-0.1.10.dist-info/METADATA
viecpro_vis-0.1.10.dist-info/RECORD
